{
    "defaultSeverity": "warn",
    "extends": [
        "tslint:recommended"
    ],
    "jsRules": {},
    "rules": {
        "ter-indent": [true, 2],
        "quotemark": [true, "single", "jsx-double"],
        "interface-name": [true, "never-prefix"],
        "object-literal-sort-keys": false,
        "prefer-for-of": false,
        "trailing-comma": false,
        "ordered-imports": false,
        "member-access": false,
        "no-console": false,
        "semicolon": [true, "always", "ignore-bound-class-methods"],
        "member-ordering": false
    },
    "rulesDirectory": []
}
